pgpack/__init__.py
pgpack/reader.py
pgpack/writer.py
pgpack/common/__init__.py
pgpack/common/cast_dataframes.py
pgpack/common/detector.py
pgpack/common/errors.py
pgpack/common/header.py
pgpack/common/metadata.py
pgpack/common/param.py
pgpack-0.3.2.2.dist-info/licenses/CHANGELOG.md
pgpack-0.3.2.2.dist-info/licenses/README.md
pgpack-0.3.2.2.dist-info/METADATA
pgpack-0.3.2.2.dist-info/WHEEL
pgpack-0.3.2.2.dist-info/top_level.txt
pgpack-0.3.2.2.dist-info/RECORD
