Metadata-Version: 2.4
Name: pgpack
Version: 0.3.2.2
Summary: PGCopy dump packed into LZ4, ZSTD or uncompressed with meta data information packed into zlib.
Home-page: https://github.com/0xMihalich/pgpack
Author: 0xMihalich
Author-email: bayanmobile87@gmail.com
License-File: README.md
License-File: CHANGELOG.md
Requires-Dist: pandas>=2.1.0
Requires-Dist: polars>=0.20.31
Requires-Dist: pgcopylib==0.2.3.2
Requires-Dist: light_compressor==0.0.2.1
Dynamic: author
Dynamic: author-email
Dynamic: description
Dynamic: description-content-type
Dynamic: home-page
Dynamic: license-file
Dynamic: summary
